[
    {
        "name": "Nongshim, Shin Ramyun Noodle Soup, 4.2 oz, 18-Count",
        "price": 19.99,
        "rating": 4.5742998123168945
    },
    {
        "name": "Nongshim, Udon Noodle Soup Bowl, 9.73 oz, 6-Count",
        "price": 18.99,
        "rating": 4.611700057983398
    },
    {
        "name": "Nongshim, Shin Black Premium Noodle Soup Cups, Spicy, 3.5 oz, 8-Count",
        "price": 14.99,
        "rating": 4.736800193786621
    },
    {
        "name": "Nissin Cup Noodles, Chicken, 2.5 oz, 24-count",
        "price": 13.99,
        "rating": 4.532199859619141
    },
    {
        "name": "Nongshim, Hot & Spicy Ramyun Noodle Bowl, 3.03 oz, 18-count",
        "price": 21.99,
        "rating": 4.605299949645996
    },
    {
        "name": "Nissin Cup Noodles, Shrimp, 2.5 oz, 24-count",
        "price": 13.99,
        "rating": 4.6209001541137695
    },
    {
        "name": "Indomie Mi Goreng Instant Fried Noodles, 3 oz, 40-count",
        "price": 23.99,
        "rating": 4.852499961853027
    },
    {
        "name": "Nissin, Top Ramen, Chicken, 3 oz, 48-Count",
        "price": 16.99,
        "rating": 4.679900169372559
    },
    {
        "name": "Nongshim, Tonkotsu Ramen Bowl, 3.56 oz, 6-Count",
        "price": 13.99,
        "rating": 4.620299816131592
    },
    {
        "name": "Samyang Buldak Ramen Carbonara, Spicy Chicken, 3.7 oz, 6-count",
        "price": 13.99,
        "rating": 4.406599998474121
    },
    {
        "name": "Nongshim, Shin Big Bowl 4.02 oz, 12-Count",
        "price": 21.99,
        "rating": 4.662300109863281
    },
    {
        "name": "Garofalo, Organic Spaghetti Noodles, 17.6 oz, 8-Count",
        "price": 13.99,
        "rating": 4.824999809265137
    },
    {
        "name": "Nongshim Ramyun Noodle Soup, YukGaeJang, Spicy Beef, 3.56 oz, 6-count",
        "price": 12.99,
        "rating": 4.904799938201904
    },
    {
        "name": "Nissin, Hot & Spicy Noodle Bowl, Chicken, 3.32 oz, 18-Count",
        "price": 20.99,
        "rating": 4.496300220489502
    },
    {
        "name": "Nissin Cup Noodles, Beef, 2.5 oz, 24-count",
        "price": 13.99,
        "rating": 4.5690999031066895
    },
    {
        "name": "Campbell's, Simply Chicken Noodle Soup, 18.6 oz, 8-Count",
        "price": 15.99,
        "rating": 4.569300174713135
    },
    {
        "name": "Snapdragon Vietnamese Pho, Beef, 2.7 oz, 9-count",
        "price": 14.99,
        "rating": 4.555200099945068
    },
    {
        "name": "Cascade Mountain Tech 4-pack Water Sports Noodle",
        "price": 49.97,
        "rating": 4.8109002113342285
    },
    {
        "name": "Lotus Foods, Organic Millet & Brown Rice Ramen, 2.5 oz, 12-Count",
        "price": 9.99,
        "rating": 4.655799865722656
    },
    {
        "name": "Dream Plush Cooling Body Pillow",
        "price": 52.99,
        "rating": 3.2221999168395996
    },
    {
        "name": "Wes-Phos 250 Neutral",
        "price": 0.0,
        "rating": null
    },
    {
        "name": "Clindamycin Phos (Twice-Daily)",
        "price": 0.0,
        "rating": null
    },
    {
        "name": "Calcium Acetate (Phos Binder)",
        "price": 0.0,
        "rating": null
    },
    {
        "name": "Clindamycin Phos-Benzoyl Perox",
        "price": 0.0,
        "rating": null
    }
]